pulathisi/__init__.py
pulathisi/blue_print.py
pulathisi/brain.py
pulathisi/pydis.py
pulathisi-0.1.3.dist-info/LICENSE
pulathisi-0.1.3.dist-info/METADATA
pulathisi-0.1.3.dist-info/WHEEL
pulathisi-0.1.3.dist-info/top_level.txt
pulathisi-0.1.3.dist-info/RECORD
